LICENSE
MANIFEST.in
README.md
setup.py
pyaramorph/__init__.py
pyaramorph/buckwalter.py
pyaramorph/command.py
pyaramorph/dictPrefixes
pyaramorph/dictStems
pyaramorph/dictSuffixes
pyaramorph/tableAB
pyaramorph/tableAC
pyaramorph/tableBC
pyaramorph/test_buckwalter.py
pyaramorph.egg-info/PKG-INFO
pyaramorph.egg-info/SOURCES.txt
pyaramorph.egg-info/dependency_links.txt
pyaramorph.egg-info/entry_points.txt
pyaramorph.egg-info/not-zip-safe
pyaramorph.egg-info/top_level.txt